examples/__init__.py
examples/get_request.py
examples/post_request.py
examples/validate_request.py
tests/__init__.py
tests/run_tests.py
tests/test_jwt_keys_directory_manager.py
tests/test_jwt_keys_memory_manager.py
tests/test_jwt_requests_validator.py
yajwt/__init__.py
yajwt/jwt_exceptions.py
yajwt/jwt_requests_validator.py
yajwt/jwt_requests_wrapper.py
yajwt/jwt_response_mapper.py
yajwt/entities/__init__.py
yajwt/entities/jwt_key.py
yajwt/entities/jwt_response.py
yajwt/entities/jwt_token.py
yajwt/keys_manager/__init__.py
yajwt/keys_manager/jwt_keys_directory_manager.py
yajwt/keys_manager/jwt_keys_manager.py
yajwt/keys_manager/jwt_keys_memory_manager.py
yajwt-0.1.0.dist-info/LICENSE.md
yajwt-0.1.0.dist-info/METADATA
yajwt-0.1.0.dist-info/WHEEL
yajwt-0.1.0.dist-info/top_level.txt
yajwt-0.1.0.dist-info/RECORD
