Metadata-Version: 2.1
Name: yajwt
Version: 0.1.0
Summary: Yet Another JWT wrapper for Python
Home-page: https://github.com/Aptoide/yajwt
Author: Nuno Nelas
Author-email: nuno.nelas@icloud.com
License: UNKNOWN
Platform: UNKNOWN
Classifier: Programming Language :: Python :: 3
Classifier: License :: OSI Approved :: GNU General Public License v3 (GPLv3)
Classifier: Operating System :: OS Independent
Requires-Python: >=3.6
Requires-Dist: PyJWT (<2.0.0,>=1.7.1)
Requires-Dist: cryptography (>=3.3.1)
Requires-Dist: dataclasses-json (>=0.5.2)
Requires-Dist: requests (>=2.23.0)
Requires-Dist: dataclasses (>=0.7) ; python_version == '3.6'
